gate/__init__.py
gate/ccxt/__init__.py
gate/ccxt/gate.py
gate/ccxt/abstract/gate.py
gate/ccxt/async_support/__init__.py
gate/ccxt/async_support/gate.py
gate/ccxt/async_support/base/__init__.py
gate/ccxt/async_support/base/exchange.py
gate/ccxt/async_support/base/throttler.py
gate/ccxt/async_support/base/ws/__init__.py
gate/ccxt/async_support/base/ws/cache.py
gate/ccxt/async_support/base/ws/client.py
gate/ccxt/async_support/base/ws/functions.py
gate/ccxt/async_support/base/ws/future.py
gate/ccxt/async_support/base/ws/order_book.py
gate/ccxt/async_support/base/ws/order_book_side.py
gate/ccxt/base/__init__.py
gate/ccxt/base/decimal_to_precision.py
gate/ccxt/base/errors.py
gate/ccxt/base/exchange.py
gate/ccxt/base/precise.py
gate/ccxt/base/types.py
gate/ccxt/pro/__init__.py
gate/ccxt/pro/gate.py
gate/ccxt/static_dependencies/README.md
gate/ccxt/static_dependencies/__init__.py
gate/ccxt/static_dependencies/bip/__init__.py
gate/ccxt/static_dependencies/bip/addr/P2PKH_addr.py
gate/ccxt/static_dependencies/bip/addr/__init__.py
gate/ccxt/static_dependencies/bip/addr/addr_dec_utils.py
gate/ccxt/static_dependencies/bip/addr/addr_key_validator.py
gate/ccxt/static_dependencies/bip/addr/iaddr_decoder.py
gate/ccxt/static_dependencies/bip/addr/iaddr_encoder.py
gate/ccxt/static_dependencies/bip/base58/__init__.py
gate/ccxt/static_dependencies/bip/base58/base58.py
gate/ccxt/static_dependencies/bip/base58/base58_ex.py
gate/ccxt/static_dependencies/bip/base58/base58_xmr.py
gate/ccxt/static_dependencies/bip/bech32/__init__.py
gate/ccxt/static_dependencies/bip/bech32/bch_bech32.py
gate/ccxt/static_dependencies/bip/bech32/bech32.py
gate/ccxt/static_dependencies/bip/bech32/bech32_base.py
gate/ccxt/static_dependencies/bip/bech32/bech32_ex.py
gate/ccxt/static_dependencies/bip/bech32/segwit_bech32.py
gate/ccxt/static_dependencies/bip/bip32/__init__.py
gate/ccxt/static_dependencies/bip/bip32/bip32_const.py
gate/ccxt/static_dependencies/bip/bip32/bip32_ex.py
gate_io_api-0.0.120.dist-info/METADATA
gate_io_api-0.0.120.dist-info/WHEEL
gate_io_api-0.0.120.dist-info/RECORD
